pypx800v5/__init__.py
pypx800v5/access_control.py
pypx800v5/const.py
pypx800v5/counter.py
pypx800v5/exceptions.py
pypx800v5/extension.py
pypx800v5/ipx800.py
pypx800v5/ipx800_io.py
pypx800v5/object.py
pypx800v5/tempo.py
pypx800v5/thermostat.py
pypx800v5/x010v.py
pypx800v5/x24d.py
pypx800v5/x4fp.py
pypx800v5/x4vr.py
pypx800v5/x8d.py
pypx800v5/x8r.py
pypx800v5/xdimmer.py
pypx800v5/xdisplay.py
pypx800v5/xpwm.py
pypx800v5/xthl.py
pypx800v5-1.4.3.dist-info/licenses/LICENSE
pypx800v5-1.4.3.dist-info/METADATA
pypx800v5-1.4.3.dist-info/WHEEL
pypx800v5-1.4.3.dist-info/top_level.txt
pypx800v5-1.4.3.dist-info/RECORD
