Metadata-Version: 2.4
Name: pypx800v5
Version: 1.4.3
Summary: Control the IPX800V5 and its extensions.
Home-page: https://github.com/aohzan/pypx800v5
Author: Aohzan
Author-email: aohzan@gmail.com
Classifier: Programming Language :: Python :: 3
Classifier: License :: OSI Approved :: MIT License
Classifier: Operating System :: OS Independent
Requires-Python: >=3.11
License-File: LICENSE
Dynamic: author
Dynamic: author-email
Dynamic: classifier
Dynamic: description
Dynamic: description-content-type
Dynamic: home-page
Dynamic: license-file
Dynamic: requires-python
Dynamic: summary
